{
  "version": "1",
  "metadata": {
    "marimo_version": "0.19.9"
  },
  "cells": [
    {
      "id": "Hbol",
      "code_hash": "602069d09c93cac2bc2b8c7df63fe0b0",
      "outputs": [
        {
          "type": "data",
          "data": {
            "text/plain": ""
          }
        }
      ],
      "console": []
    },
    {
      "id": "eVjj",
      "code_hash": "51b7571aa957d1c7280856003e9c58ab",
      "outputs": [
        {
          "type": "data",
          "data": {
            "text/plain": ""
          }
        }
      ],
      "console": []
    },
    {
      "id": "ZHRD",
      "code_hash": "41bf35546c036f429902934f44fb3538",
      "outputs": [
        {
          "type": "data",
          "data": {
            "text/html": "<div style='display: flex;flex: 1;flex-direction: row;justify-content: space-between;align-items: normal;flex-wrap: nowrap;gap: 0.5rem'><marimo-ui-element object-id='eVjj-3' random-id='010f942a-20e5-a3a5-51d3-eb1563a7cf17'><marimo-slider data-initial-value='0' data-label='&quot;&lt;span class=&#92;&quot;markdown prose dark:prose-invert contents&#92;&quot;&gt;&lt;span class=&#92;&quot;paragraph&#92;&quot;&gt;Start&lt;/span&gt;&lt;/span&gt;&quot;' data-start='0' data-stop='100' data-steps='[]' data-debounce='false' data-disabled='false' data-orientation='&quot;horizontal&quot;' data-show-value='false' data-include-input='false' data-full-width='false'></marimo-slider></marimo-ui-element><marimo-ui-element object-id='eVjj-4' random-id='3cf98ad1-f6c6-ec0e-2f09-e3ea16876805'><marimo-slider data-initial-value='50' data-label='&quot;&lt;span class=&#92;&quot;markdown prose dark:prose-invert contents&#92;&quot;&gt;&lt;span class=&#92;&quot;paragraph&#92;&quot;&gt;Stop&lt;/span&gt;&lt;/span&gt;&quot;' data-start='0' data-stop='100' data-steps='[]' data-debounce='false' data-disabled='false' data-orientation='&quot;horizontal&quot;' data-show-value='false' data-include-input='false' data-full-width='false'></marimo-slider></marimo-ui-element><marimo-ui-element object-id='eVjj-5' random-id='b434e937-63ab-faa3-18ab-e17c9786e485'><marimo-slider data-initial-value='1' data-label='&quot;&lt;span class=&#92;&quot;markdown prose dark:prose-invert contents&#92;&quot;&gt;&lt;span class=&#92;&quot;paragraph&#92;&quot;&gt;Step / Num&lt;/span&gt;&lt;/span&gt;&quot;' data-start='0' data-stop='100' data-steps='[]' data-debounce='false' data-disabled='false' data-orientation='&quot;horizontal&quot;' data-show-value='false' data-include-input='false' data-full-width='false'></marimo-slider></marimo-ui-element></div>"
          }
        }
      ],
      "console": []
    },
    {
      "id": "esuA",
      "code_hash": "a46fdc7468e9a70fc1ee216a8aa85bf7",
      "outputs": [
        {
          "type": "data",
          "data": {
            "text/plain": ""
          }
        }
      ],
      "console": [
        {
          "type": "stream",
          "name": "stdout",
          "text": "0 50 12\n",
          "mimetype": "text/plain"
        }
      ]
    },
    {
      "id": "UCvJ",
      "code_hash": "e4f40c2f7b2960f69222775ce6dff62d",
      "outputs": [
        {
          "type": "data",
          "data": {
            "text/html": "<marimo-ui-element object-id='UCvJ-0' random-id='13fb67ad-8c52-ea5b-30b1-2c7353b9e2b2'><marimo-table data-initial-value='[]' data-label='null' data-data='&quot;[{&#92;&quot;x&#92;&quot;:0.0,&#92;&quot;y&#92;&quot;:0.0},{&#92;&quot;x&#92;&quot;:4.545454545454546,&#92;&quot;y&#92;&quot;:0.0},{&#92;&quot;x&#92;&quot;:9.090909090909092,&#92;&quot;y&#92;&quot;:0.0}]&quot;' data-total-rows='3' data-total-columns='2' data-max-columns='50' data-banner-text='&quot;&quot;' data-pagination='true' data-page-size='10' data-field-types='[[&quot;x&quot;,[&quot;number&quot;,&quot;float64&quot;]],[&quot;y&quot;,[&quot;number&quot;,&quot;float64&quot;]]]' data-show-filters='true' data-show-download='true' data-show-column-summaries='false' data-show-data-types='true' data-show-page-size-selector='false' data-show-column-explorer='true' data-show-chart-builder='true' data-row-headers='[]' data-has-stable-row-id='false' data-lazy='false' data-preload='false'></marimo-table></marimo-ui-element>"
          }
        }
      ],
      "console": []
    },
    {
      "id": "TIvc",
      "code_hash": "94fa84b935a2a3d8676eea8facc513b9",
      "outputs": [
        {
          "type": "data",
          "data": {
            "application/vnd.vegalite.v6+json": "{\n  \"$schema\": \"https://vega.github.io/schema/vega-lite/v6.1.0.json\",\n  \"config\": {\n    \"view\": {\n      \"continuousHeight\": 300,\n      \"continuousWidth\": 300\n    }\n  },\n  \"data\": {\n    \"name\": \"data-949005c0ecf3b801a3d4e21b65692153\"\n  },\n  \"datasets\": {\n    \"data-949005c0ecf3b801a3d4e21b65692153\": [\n      {\n        \"x\": 0.0,\n        \"y\": 0.0\n      },\n      {\n        \"x\": 4.545454545454546,\n        \"y\": 0.0\n      },\n      {\n        \"x\": 9.090909090909092,\n        \"y\": 0.0\n      },\n      {\n        \"x\": 13.636363636363637,\n        \"y\": 0.0\n      },\n      {\n        \"x\": 18.181818181818183,\n        \"y\": 0.0\n      },\n      {\n        \"x\": 22.72727272727273,\n        \"y\": 0.0\n      },\n      {\n        \"x\": 27.272727272727273,\n        \"y\": 0.0\n      },\n      {\n        \"x\": 31.81818181818182,\n        \"y\": 0.0\n      },\n      {\n        \"x\": 36.36363636363637,\n        \"y\": 0.0\n      },\n      {\n        \"x\": 40.909090909090914,\n        \"y\": 0.0\n      },\n      {\n        \"x\": 45.45454545454546,\n        \"y\": 0.0\n      },\n      {\n        \"x\": 50.0,\n        \"y\": 0.0\n      }\n    ]\n  },\n  \"encoding\": {\n    \"x\": {\n      \"field\": \"x\",\n      \"type\": \"quantitative\"\n    },\n    \"y\": {\n      \"field\": \"y\",\n      \"type\": \"quantitative\"\n    }\n  },\n  \"mark\": {\n    \"type\": \"point\"\n  },\n  \"params\": [\n    {\n      \"bind\": \"scales\",\n      \"name\": \"param_1e9efca18e7a2868\",\n      \"select\": {\n        \"encodings\": [\n          \"x\",\n          \"y\"\n        ],\n        \"type\": \"interval\"\n      }\n    }\n  ],\n  \"usermeta\": {\n    \"embedOptions\": {}\n  },\n  \"width\": \"container\"\n}"
          }
        }
      ],
      "console": []
    }
  ]
}